README.md
setup.cfg
setup.py
higrid/Microphone.py
higrid/TreeClusteri.py
higrid/Treei.py
higrid/__init__.py
higrid/dpd.py
higrid/emulate.py
higrid/higridestimate.py
higrid/shd.py
higrid/testpos3d.py
higrid/treeutils.py
higrid/utils.py
higrid.egg-info/PKG-INFO
higrid.egg-info/SOURCES.txt
higrid.egg-info/dependency_links.txt
higrid.egg-info/requires.txt
higrid.egg-info/top_level.txt