Metadata-Version: 1.1
Name: higrid
Version: 0.1.1
Summary: Hierarchical Grid Refinement (HiGRID): Multiple source DOA Estimation with Spherical Microphone Arrays
Home-page: https://github.com/metu-sparg/higrid
Author: Huseyin Hacihabiboglu (METU SPARG)
Author-email: husshho+pypi@gmail.com
License: BSD 3-Clause License
Download-URL: https://github.com/metu-sparg/higrid/archive/higrid_v01.tar.gz
Keywords: Localization,DOA estimation,Eigenmike,Acoustics,Microphone array,Sound
Platform: UNKNOWN
Classifier: Development Status :: 3 - Alpha
Classifier: Intended Audience :: Science/Research
Classifier: License :: OSI Approved :: BSD License
Classifier: Programming Language :: Python
Classifier: Programming Language :: Python :: 3
Classifier: Programming Language :: Python :: 3.6
Classifier: Programming Language :: Python :: 3.7
Classifier: Programming Language :: Python :: 3 :: Only
Classifier: Environment :: Console
Classifier: Operating System :: MacOS
Classifier: Operating System :: POSIX :: Linux
Classifier: Topic :: Multimedia :: Sound/Audio
Classifier: Topic :: Multimedia :: Sound/Audio :: Analysis
Classifier: Topic :: Multimedia :: Sound/Audio :: Capture/Recording
